gradle.properties
hexdoc_hexical/__gradle_version__.py
hexdoc_hexical/__init__.py
hexdoc_hexical/__version__.py
hexdoc_hexical/_hooks.py
hexdoc_hexical/py.typed
hexdoc_hexical/_export/.gitignore
hexdoc_hexical/_export/__init__.py
hexdoc_hexical/_export/generated/__init__.py
hexdoc_hexical/_export/generated/hexical.hexdoc.json
hexdoc_hexical/_export/generated/hexical.patterns.hexdoc.json
hexdoc_hexical/_export/generated/assets/hexcasting/lang/en_us.flatten.json5
hexdoc_hexical/_export/generated/assets/hexcasting/patchouli_books/thehexbook/en_us/categories/lamp.json
hexdoc_hexical/_export/generated/assets/hexcasting/patchouli_books/thehexbook/en_us/categories/scrying.json
hexdoc_hexical/_export/generated/assets/hexcasting/patchouli_books/thehexbook/en_us/entries/basic/hexical_changes.json
hexdoc_hexical/_export/generated/assets/hexcasting/patchouli_books/thehexbook/en_us/entries/items/animated_scroll.json
hexdoc_hexical/_export/generated/assets/hexcasting/patchouli_books/thehexbook/en_us/entries/items/grimoire.json
hexdoc_hexical/_export/generated/assets/hexcasting/patchouli_books/thehexbook/en_us/entries/items/hex_candles.json
hexdoc_hexical/_export/generated/assets/hexcasting/patchouli_books/thehexbook/en_us/entries/items/media_jar.json
hexdoc_hexical/_export/generated/assets/hexcasting/patchouli_books/thehexbook/en_us/entries/lamp/arch_lamps.json
hexdoc_hexical/_export/generated/assets/hexcasting/patchouli_books/thehexbook/en_us/entries/lamp/mysterious_lamp.json
hexdoc_hexical/_export/generated/assets/hexcasting/patchouli_books/thehexbook/en_us/entries/lamp/replacement.json
hexdoc_hexical/_export/generated/assets/hexcasting/patchouli_books/thehexbook/en_us/entries/patterns/akashic_utils.json
hexdoc_hexical/_export/generated/assets/hexcasting/patchouli_books/thehexbook/en_us/entries/patterns/enlightened_patterns.json
hexdoc_hexical/_export/generated/assets/hexcasting/patchouli_books/thehexbook/en_us/entries/patterns/metaevals.json
hexdoc_hexical-1.5.0.1.0.0.dist-info/METADATA
hexdoc_hexical-1.5.0.1.0.0.dist-info/WHEEL
hexdoc_hexical-1.5.0.1.0.0.dist-info/entry_points.txt
hexdoc_hexical-1.5.0.1.0.0.dist-info/licenses/LICENSE
hexdoc_hexical-1.5.0.1.0.0.dist-info/RECORD
