Metadata-Version: 2.4
Name: hexdoc-hexical
Version: 1.5.0.1.0.0
Summary: Python web book docgen and hexdoc plugin for Hexical.
Project-URL: Homepage, https://miyucomics.github.io/hexical/
Project-URL: Source, https://github.com/miyucomics/hexical
Author: miyucomics
License-File: LICENSE
Keywords: hexdoc
Requires-Python: >=3.11
Requires-Dist: hexdoc-hexcasting~=0.11.2.1.0.dev20
Provides-Extra: dev
Requires-Dist: ruff~=0.1.4; extra == 'dev'
